XPathMongoCompiler/__init__.py
XPathMongoCompiler/compiler.py
XPathMongoCompiler-0.1.1.dist-info/LICENSE
XPathMongoCompiler-0.1.1.dist-info/METADATA
XPathMongoCompiler-0.1.1.dist-info/WHEEL
XPathMongoCompiler-0.1.1.dist-info/top_level.txt
XPathMongoCompiler-0.1.1.dist-info/RECORD
